{
  "hash": "512c9aae",
  "configHash": "224d15f0",
  "lockfileHash": "69d6ab23",
  "browserHash": "85365fd2",
  "optimized": {
    "vue": {
      "src": "../../../node_modules/vue/dist/vue.runtime.esm-bundler.js",
      "file": "vue.js",
      "fileHash": "0c1114fd",
      "needsInterop": false
    },
    "vitepress > @vue/devtools-api": {
      "src": "../../../node_modules/@vue/devtools-api/dist/index.js",
      "file": "vitepress___@vue_devtools-api.js",
      "fileHash": "e957f526",
      "needsInterop": false
    },
    "vitepress > @vueuse/core": {
      "src": "../../../node_modules/@vueuse/core/index.mjs",
      "file": "vitepress___@vueuse_core.js",
      "fileHash": "78b1a07c",
      "needsInterop": false
    },
    "vitepress-plugin-tabs/client": {
      "src": "../../../node_modules/vitepress-plugin-tabs/src/client/index.ts",
      "file": "vitepress-plugin-tabs_client.js",
      "fileHash": "6934013c",
      "needsInterop": false
    }
  },
  "chunks": {
    "chunk-OL6HMLMB": {
      "file": "chunk-OL6HMLMB.js"
    }
  }
}